wagtail_2fa/__init__.py
wagtail_2fa/apps.py
wagtail_2fa/forms.py
wagtail_2fa/middleware.py
wagtail_2fa/mixins.py
wagtail_2fa/urls.py
wagtail_2fa/utils.py
wagtail_2fa/views.py
wagtail_2fa/wagtail_hooks.py
wagtail_2fa/locale/en/LC_MESSAGES/django.mo
wagtail_2fa/locale/en/LC_MESSAGES/django.po
wagtail_2fa/locale/nl/LC_MESSAGES/django.mo
wagtail_2fa/locale/nl/LC_MESSAGES/django.po
wagtail_2fa/migrations/0001_initial.py
wagtail_2fa/migrations/__init__.py
wagtail_2fa/templates/wagtail_2fa/device_confirm_delete.html
wagtail_2fa/templates/wagtail_2fa/device_form.html
wagtail_2fa/templates/wagtail_2fa/device_list.html
wagtail_2fa/templates/wagtail_2fa/otp_form.html
wagtail_2fa/templates/wagtail_2fa/legacy/otp_form.html
wagtail_2fa_v6-1.0.7.dist-info/licenses/LICENSE
wagtail_2fa_v6-1.0.7.dist-info/METADATA
wagtail_2fa_v6-1.0.7.dist-info/WHEEL
wagtail_2fa_v6-1.0.7.dist-info/top_level.txt
wagtail_2fa_v6-1.0.7.dist-info/RECORD
